onomancer/__init__.py
onomancer/predict.py
onomancer/data/F.txt
onomancer/data/M.txt
onomancer/data/N.txt
onomancer/data/model.bin
onomancer/utils/__init__.py
tests/__init__.py
tests/test.py
onomancer-0.0.5.dist-info/LICENSE
onomancer-0.0.5.dist-info/METADATA
onomancer-0.0.5.dist-info/WHEEL
onomancer-0.0.5.dist-info/top_level.txt
onomancer-0.0.5.dist-info/RECORD
