Metadata-Version: 2.1
Name: onomancer
Version: 0.0.5
Summary: Lookup and/or predict gender of given first name.
Home-page: https://github.com/parthmaul/onomancer
Author: Parth Jalundhwala
Author-email: pjalundh@gmail.com
License: UNKNOWN
Keywords: gender,predict,names,model,nlp
Platform: UNKNOWN
Classifier: Programming Language :: Python :: 3
Classifier: License :: OSI Approved :: MIT License
Classifier: Operating System :: OS Independent
Requires-Python: >=3.6
Requires-Dist: fasttext (==0.9.2)
Requires-Dist: setuptools (>=46.0.0)
